<?xml version="1.0"?>
<!-- This file is part stock_supply_sale module for Tryton.
The COPYRIGHT file at the top level of this repository contains the full
copyright notices and license terms. -->
<form string="Create Purchase Requests from Sales" col="2" cursor="warehouse">
    <notebook>
        <page string="General Parameters" id="general" col="2">
            <label name="days_for_average"/>
            <field name="days_for_average"/>
            <label name="minimum_days"/>
            <field name="minimum_days"/>
            <label name="quantity_average"/>
            <field name="quantity_average"/>
            <label name="warehouse"/>
            <field name="warehouse"/>
            <label name="sporadic_supplier"/>
            <field name="sporadic_supplier"/>
        </page>
        <page string="Filters" id="filters" col="2">
            <notebook>
                <page string="Suppliers" id="suppliers">
                    <field name="suppliers"/>
                </page>
                <page string="Manufacturers" id="manufacturers">
                    <field name="manufacturers"/>
                </page>
                <page string="Categories" id="categories">
                    <field name="categories"/>
                </page>
                <page string="Products" id="products">
                    <field name="products"/>
                </page>
            </notebook>
        </page>
    </notebook>
</form>
